azure/ai/projects/__init__.py
azure/ai/projects/_client.py
azure/ai/projects/_configuration.py
azure/ai/projects/_model_base.py
azure/ai/projects/_patch.py
azure/ai/projects/_serialization.py
azure/ai/projects/_validation.py
azure/ai/projects/_vendor.py
azure/ai/projects/_version.py
azure/ai/projects/py.typed
azure/ai/projects/_utils/__init__.py
azure/ai/projects/_utils/model_base.py
azure/ai/projects/_utils/serialization.py
azure/ai/projects/aio/__init__.py
azure/ai/projects/aio/_client.py
azure/ai/projects/aio/_configuration.py
azure/ai/projects/aio/_patch.py
azure/ai/projects/aio/_vendor.py
azure/ai/projects/aio/operations/__init__.py
azure/ai/projects/aio/operations/_operations.py
azure/ai/projects/aio/operations/_patch.py
azure/ai/projects/aio/operations/_patch_connections_async.py
azure/ai/projects/aio/operations/_patch_datasets_async.py
azure/ai/projects/aio/operations/_patch_telemetry_async.py
azure/ai/projects/models/__init__.py
azure/ai/projects/models/_enums.py
azure/ai/projects/models/_models.py
azure/ai/projects/models/_patch.py
azure/ai/projects/models/_patch_evaluations.py
azure/ai/projects/operations/__init__.py
azure/ai/projects/operations/_operations.py
azure/ai/projects/operations/_patch.py
azure/ai/projects/operations/_patch_connections.py
azure/ai/projects/operations/_patch_datasets.py
azure/ai/projects/operations/_patch_telemetry.py
azure_ai_projects-1.1.0b3.dist-info/licenses/LICENSE
azure_ai_projects-1.1.0b3.dist-info/METADATA
azure_ai_projects-1.1.0b3.dist-info/WHEEL
azure_ai_projects-1.1.0b3.dist-info/top_level.txt
azure_ai_projects-1.1.0b3.dist-info/RECORD
