Metadata-Version: 2.4
Name: azure-ai-projects
Version: 1.1.0b3
Summary: Microsoft Azure AI Projects Client Library for Python
Home-page: https://github.com/Azure/azure-sdk-for-python/tree/main/sdk/ai/azure-ai-projects
Author: Microsoft Corporation
Author-email: azpysdkhelp@microsoft.com
License: MIT License
Keywords: azure sdk,azure,ai,agents,foundry,inference,chat completion,project,evaluation
Classifier: Development Status :: 4 - Beta
Classifier: Programming Language :: Python
Classifier: Programming Language :: Python :: 3 :: Only
Classifier: Programming Language :: Python :: 3
Classifier: Programming Language :: Python :: 3.9
Classifier: Programming Language :: Python :: 3.10
Classifier: Programming Language :: Python :: 3.11
Classifier: Programming Language :: Python :: 3.12
Classifier: Programming Language :: Python :: 3.13
Classifier: License :: OSI Approved :: MIT License
Classifier: Topic :: Scientific/Engineering :: Artificial Intelligence
Requires-Python: >=3.9
License-File: LICENSE
Requires-Dist: isodate>=0.6.1
Requires-Dist: azure-core>=1.30.0
Requires-Dist: typing-extensions>=4.12.2
Requires-Dist: azure-storage-blob>=12.15.0
Requires-Dist: azure-ai-agents>=1.2.0b3
Dynamic: author
Dynamic: author-email
Dynamic: classifier
Dynamic: description
Dynamic: description-content-type
Dynamic: home-page
Dynamic: keywords
Dynamic: license
Dynamic: license-file
Dynamic: requires-dist
Dynamic: requires-python
Dynamic: summary
